{"data":{"site":{"siteMetadata":{"testTemplate":"success <- function(text) {\n    cat(paste(\"\\033[32m\", text, \"\\033[0m\", sep = \"\"))\n}\n\n.solution <- \"${solutionEscaped}\"\n\n${solution}\n\n${test}\ntryCatch({\n    test()\n}, error = function(e) {\n    cat(paste(\"\\033[31m\", e[1], \"\\033[0m\", sep = \"\"))\n})","juniper":{"repo":"HeidiSeibold/course-starter-r","branch":"binder","kernelType":"ir","lang":"r","debug":false}}},"allCode":{"edges":[{"node":{"name":"exc_01_03","code":"# load the mlr3 package\nlibrary(_____)\n\n# create a classification tree learner\n\nlrn =\n"}},{"node":{"name":"solution_01_03","code":"library(mlr3)\n\nlrn = mlr_learners$get(\"classif.rpart\")\n\n"}},{"node":{"name":"test_01_03","code":"test <- function() {\n    # Here we can either check objects created in the solution code, or the\n    # string value of the solution, available as .solution. See the testTemplate\n    # in the meta.json for details.\n    if (! \"mlr3\" %in% .packages())\n      stop(\"mlr3 is not loaded\")\n\n    success(\"Well done!\")\n}\n"}}]}}}